yepcord/__init__.py
yepcord-0.0.1.dist-info/METADATA
yepcord-0.0.1.dist-info/WHEEL
yepcord-0.0.1.dist-info/RECORD
