Metadata-Version: 2.1
Name: yepcord
Version: 0.0.1
Summary: YEPCord - Free open source selfhostable fully discord-compatible chat
License: AGPL-3.0
Author: RuslanUC
Author-email: dev_ruslan_uc@protonmail.com
Requires-Python: >=3.9,<4.0
Classifier: License :: OSI Approved :: GNU Affero General Public License v3
Classifier: Programming Language :: Python :: 3
Classifier: Programming Language :: Python :: 3.9
Classifier: Programming Language :: Python :: 3.10
Classifier: Programming Language :: Python :: 3.11
